[
    {
        "month":"",
        "year":"1",
        
        "title":"BİLGİLER DOLDURULARAK GEREKLİ SERTİFİKALAR VE BELGELER BİR KOMİTE TARAFINDAN ONAYLANIR."
    },
    {
        "month":"",
        "year":"2",
        "title":"KURUM YETKİLİSİNİN CÜZDANINDAN BELGELER SCIMATİC HİBRİT BLOKZİNCİR ÜZERİNE BASILIR.YÜKLENEN BELGE KİŞİNİN KRİPTO CÜZDAN ADRESİNE GİDER."
    },
    {
        "month":"",
        "year":"3",
        "title":"İŞ BAŞVURULARINDA KRİPTO CÜZDAN ADRESİYLE SORGULAMA KISMINDAN BELGELERİNİ SORGULATABİLİR. "
    },
    {
        "month":"",
        "year":"4",
        "title":"KİŞİ KRİPTO CÜZDAN ADRESİNDEN BELGESİNE HER YERDEN ULAŞABİLİR."
    }
]